{"type":"Topology","bbox":[3.39583,48.51517,5.03968,49.40758],"objects":{"collection":{"type":"GeometryCollection","geometries":[{"type":"Polygon","arcs":[[0,1,2,3,4]],"properties":{"code":"51001","nom":"Châlons-en-Champagne"}},{"type":"Polygon","arcs":[[5,-4,6]],"properties":{"code":"51002","nom":"Épernay"}},{"type":"Polygon","arcs":[[-5,-6,7]],"properties":{"code":"51003","nom":"Reims"}},{"type":"Polygon","arcs":[[8,-2]],"properties":{"code":"51004","nom":"Vitry-le-François"}}]}},"arcs":[[],[],[],[],[],[],[],[],[]]}